polire/__init__.py
polire/constants.py
polire/base/__init__.py
polire/base/base.py
polire/custom/__init__.py
polire/custom/custom.py
polire/gp/__init__.py
polire/gp/gp.py
polire/idw/__init__.py
polire/idw/idw.py
polire/kriging/__init__.py
polire/kriging/kriging.py
polire/natural_neighbors/__init__.py
polire/natural_neighbors/natural_neighbors.py
polire/nsgp/__init__.py
polire/nsgp/nsgp.py
polire/preprocessing/__init__.py
polire/preprocessing/preprocessing.py
polire/random/__init__.py
polire/random/random.py
polire/spatial/__init__.py
polire/spatial/spatial.py
polire/spline/__init__.py
polire/spline/bspline.py
polire/trend/__init__.py
polire/trend/polynomials.py
polire/trend/trend.py
polire/utils/__init__.py
polire/utils/distance.py
polire/utils/gridding.py
tests/__init__.py
tests/test_basic.py
polire-0.1.3.dist-info/LICENSE
polire-0.1.3.dist-info/METADATA
polire-0.1.3.dist-info/WHEEL
polire-0.1.3.dist-info/top_level.txt
polire-0.1.3.dist-info/RECORD
